{
  "v": "5.12.1",
  "fr": 30,
  "ip": 0,
  "op": 60,
  "w": 500,
  "h": 500,
  "nm": "Comp 1",
  "ddd": 0,
  "assets": [],
  "layers": [
    {
      "ddd": 0,
      "ind": 1,
      "ty": 4,
      "nm": "line",
      "sr": 1,
      "ks": {
        "o": {
          "a": 1,
          "k": [
            { "i": { "x": [0.833], "y": [0.833] }, "o": { "x": [0.167], "y": [0.167] }, "t": 79, "s": [100] },
            { "t": 85, "s": [0] }
          ],
          "ix": 11
        },
        "r": { "a": 0, "k": 0, "ix": 10 },
        "p": { "a": 0, "k": [250, 250, 0], "ix": 2, "l": 2 },
        "a": { "a": 0, "k": [-29.031, -33.5, 0], "ix": 1, "l": 2 },
        "s": { "a": 0, "k": [100, 100, 100], "ix": 6, "l": 2 }
      },
      "ao": 0,
      "hasMask": true,
      "masksProperties": [
        {
          "inv": false,
          "mode": "s",
          "pt": {
            "a": 1,
            "k": [
              {
                "i": { "x": 0.128, "y": 1 },
                "o": { "x": 0.167, "y": 0.167 },
                "t": 4,
                "s": [
                  {
                    "i": [
                      [0, 0],
                      [0, 0],
                      [0, 0],
                      [0, 0]
                    ],
                    "o": [
                      [0, 0],
                      [0, 0],
                      [0, 0],
                      [0, 0]
                    ],
                    "v": [
                      [201.969, -104.5],
                      [-236.031, -104.5],
                      [-236.031, 64],
                      [201.969, 64]
                    ],
                    "c": true
                  }
                ]
              },
              {
                "t": 79,
                "s": [
                  {
                    "i": [
                      [0, 0],
                      [0, 0],
                      [0, 0],
                      [0, 0]
                    ],
                    "o": [
                      [0, 0],
                      [0, 0],
                      [0, 0],
                      [0, 0]
                    ],
                    "v": [
                      [259.969, -104.5],
                      [238.969, -104.5],
                      [238.969, 64],
                      [259.969, 64]
                    ],
                    "c": true
                  }
                ]
              }
            ],
            "ix": 1
          },
          "o": { "a": 0, "k": 100, "ix": 3 },
          "x": { "a": 0, "k": 0, "ix": 4 },
          "nm": "Mask 1"
        },
        {
          "inv": false,
          "mode": "i",
          "pt": {
            "a": 1,
            "k": [
              {
                "i": { "x": 0.123, "y": 1 },
                "o": { "x": 0.167, "y": 0.167 },
                "t": 9,
                "s": [
                  {
                    "i": [
                      [0, 0],
                      [0, 0],
                      [0, 0],
                      [0, 0]
                    ],
                    "o": [
                      [0, 0],
                      [0, 0],
                      [0, 0],
                      [0, 0]
                    ],
                    "v": [
                      [303.469, -104.5],
                      [-236.031, -104.5],
                      [-236.031, 64],
                      [303.469, 64]
                    ],
                    "c": true
                  }
                ]
              },
              {
                "t": 87,
                "s": [
                  {
                    "i": [
                      [0, 0],
                      [0, 0],
                      [0, 0],
                      [0, 0]
                    ],
                    "o": [
                      [0, 0],
                      [0, 0],
                      [0, 0],
                      [0, 0]
                    ],
                    "v": [
                      [287.969, -104.5],
                      [254.969, -104.5],
                      [254.969, 64],
                      [287.969, 64]
                    ],
                    "c": true
                  }
                ]
              }
            ],
            "ix": 1
          },
          "o": { "a": 0, "k": 100, "ix": 3 },
          "x": { "a": 0, "k": 0, "ix": 4 },
          "nm": "Mask 2"
        }
      ],
      "shapes": [
        {
          "ty": "gr",
          "it": [
            {
              "ind": 0,
              "ty": "sh",
              "ix": 1,
              "ks": {
                "a": 0,
                "k": {
                  "i": [
                    [0, 0.25],
                    [0, 0],
                    [0, 0],
                    [0, 0],
                    [0, 0],
                    [0, 0],
                    [0, 0],
                    [0, 0],
                    [0, 0],
                    [0, 0],
                    [0, 0],
                    [0, 0],
                    [0, 0],
                    [0, 0],
                    [0, 0],
                    [0, 0],
                    [0, 0],
                    [0, 0],
                    [0, 0],
                    [0, 0],
                    [0, 0],
                    [0, 0],
                    [0, 0],
                    [0, 0],
                    [0, 0],
                    [0, 0],
                    [0, 0],
                    [0, 0],
                    [0, 0],
                    [0, 0],
                    [0, 0],
                    [0, 0],
                    [0, 0],
                    [0, 0],
                    [0, 0],
                    [0, 0],
                    [0, 0],
                    [0, 0],
                    [0, 0],
                    [0, 0],
                    [0, 0],
                    [0, 0],
                    [0, 0],
                    [0, 0],
                    [0, 0],
                    [0, 0]
                  ],
                  "o": [
                    [0, -0.25],
                    [0, 0],
                    [0, 0],
                    [0, 0],
                    [0, 0],
                    [0, 0],
                    [0, 0],
                    [0, 0],
                    [0, 0],
                    [0, 0],
                    [0, 0],
                    [0, 0],
                    [0, 0],
                    [0, 0],
                    [0, 0],
                    [0, 0],
                    [0, 0],
                    [0, 0],
                    [0, 0],
                    [0, 0],
                    [0, 0],
                    [0, 0],
                    [0, 0],
                    [0, 0],
                    [0, 0],
                    [0, 0],
                    [0, 0],
                    [0, 0],
                    [0, 0],
                    [0, 0],
                    [0, 0],
                    [0, 0],
                    [0, 0],
                    [0, 0],
                    [0, 0],
                    [0, 0],
                    [0, 0],
                    [0, 0],
                    [0, 0],
                    [0, 0],
                    [0, 0],
                    [0, 0],
                    [0, 0],
                    [0, 0],
                    [0, 0],
                    [0, 0]
                  ],
                  "v": [
                    [-219.688, -20.75],
                    [-189, -21],
                    [-179.875, -26],
                    [-171.5, -21],
                    [-163, -21],
                    [-160.125, -15.125],
                    [-157, -21],
                    [-150.125, -21],
                    [-146.25, -33],
                    [-140.625, -21],
                    [-135.25, -21],
                    [-133.75, -17.5],
                    [-127.125, -87.375],
                    [-117.75, 20.625],
                    [-112.875, -21],
                    [-100.375, -21],
                    [-88, -35],
                    [-77.625, -21],
                    [-45, -21],
                    [-36.125, -26.25],
                    [-25.875, -21],
                    [-17.875, -21],
                    [-14.875, -14.75],
                    [-12.75, -21],
                    [-5.875, -21],
                    [-1, -32.875],
                    [4.125, -21],
                    [9, -21],
                    [10.875, -16.25],
                    [18.375, -87.5],
                    [26.125, 20],
                    [32.25, -21],
                    [77.375, -21],
                    [85.75, -26.375],
                    [92.25, -21],
                    [101.25, -21],
                    [105.5, -14.625],
                    [108.375, -21],
                    [114.5, -21],
                    [121.25, -32.5],
                    [125.5, -21],
                    [134.625, -21],
                    [140.25, -14.25],
                    [146.625, -88.125],
                    [156.5, 21.125],
                    [161.625, 9.125]
                  ],
                  "c": false
                },
                "ix": 2
              },
              "nm": "Path 1",
              "mn": "ADBE Vector Shape - Group",
              "hd": false
            },
            {
              "ty": "st",
              "c": { "a": 0, "k": [0.910552978516, 0.154968261719, 0.218963623047, 1], "ix": 3 },
              "o": { "a": 0, "k": 100, "ix": 4 },
              "w": { "a": 0, "k": 0.5, "ix": 5 },
              "lc": 1,
              "lj": 1,
              "ml": 4,
              "bm": 0,
              "nm": "Stroke 1",
              "mn": "ADBE Vector Graphic - Stroke",
              "hd": false
            },
            {
              "ty": "tr",
              "p": { "a": 0, "k": [0, 0], "ix": 2 },
              "a": { "a": 0, "k": [0, 0], "ix": 1 },
              "s": { "a": 0, "k": [100, 100], "ix": 3 },
              "r": { "a": 0, "k": 0, "ix": 6 },
              "o": { "a": 0, "k": 100, "ix": 7 },
              "sk": { "a": 0, "k": 0, "ix": 4 },
              "sa": { "a": 0, "k": 0, "ix": 5 },
              "nm": "Transform"
            }
          ],
          "nm": "Shape 1",
          "np": 3,
          "cix": 2,
          "bm": 0,
          "ix": 1,
          "mn": "ADBE Vector Group",
          "hd": false
        }
      ],
      "ip": 4,
      "op": 904,
      "st": 4,
      "ct": 1,
      "bm": 0
    },
    {
      "ddd": 0,
      "ind": 2,
      "ty": 4,
      "nm": "line 3",
      "sr": 1,
      "ks": {
        "o": {
          "a": 1,
          "k": [
            { "i": { "x": [0.833], "y": [0.833] }, "o": { "x": [0.167], "y": [0.167] }, "t": 78, "s": [100] },
            { "t": 85, "s": [0] }
          ],
          "ix": 11
        },
        "r": { "a": 0, "k": 0, "ix": 10 },
        "p": { "a": 0, "k": [250, 250, 0], "ix": 2, "l": 2 },
        "a": { "a": 0, "k": [-29.031, -33.5, 0], "ix": 1, "l": 2 },
        "s": { "a": 0, "k": [100, 100, 100], "ix": 6, "l": 2 }
      },
      "ao": 0,
      "hasMask": true,
      "masksProperties": [
        {
          "inv": false,
          "mode": "s",
          "pt": {
            "a": 1,
            "k": [
              {
                "i": { "x": 0.126, "y": 1 },
                "o": { "x": 0.167, "y": 0.167 },
                "t": 2,
                "s": [
                  {
                    "i": [
                      [0, 0],
                      [0, 0],
                      [0, 0],
                      [0, 0]
                    ],
                    "o": [
                      [0, 0],
                      [0, 0],
                      [0, 0],
                      [0, 0]
                    ],
                    "v": [
                      [201.969, -104.5],
                      [-236.031, -104.5],
                      [-236.031, 64],
                      [201.969, 64]
                    ],
                    "c": true
                  }
                ]
              },
              {
                "t": 78,
                "s": [
                  {
                    "i": [
                      [0, 0],
                      [0, 0],
                      [0, 0],
                      [0, 0]
                    ],
                    "o": [
                      [0, 0],
                      [0, 0],
                      [0, 0],
                      [0, 0]
                    ],
                    "v": [
                      [271.469, -104.5],
                      [250.469, -104.5],
                      [250.469, 64],
                      [271.469, 64]
                    ],
                    "c": true
                  }
                ]
              }
            ],
            "ix": 1
          },
          "o": { "a": 0, "k": 100, "ix": 3 },
          "x": { "a": 0, "k": 0, "ix": 4 },
          "nm": "Mask 1"
        },
        {
          "inv": false,
          "mode": "i",
          "pt": {
            "a": 1,
            "k": [
              {
                "i": { "x": 0.123, "y": 1 },
                "o": { "x": 0.167, "y": 0.167 },
                "t": 7,
                "s": [
                  {
                    "i": [
                      [0, 0],
                      [0, 0],
                      [0, 0],
                      [0, 0]
                    ],
                    "o": [
                      [0, 0],
                      [0, 0],
                      [0, 0],
                      [0, 0]
                    ],
                    "v": [
                      [303.469, -104.5],
                      [-236.031, -104.5],
                      [-236.031, 64],
                      [303.469, 64]
                    ],
                    "c": true
                  }
                ]
              },
              {
                "t": 85,
                "s": [
                  {
                    "i": [
                      [0, 0],
                      [0, 0],
                      [0, 0],
                      [0, 0]
                    ],
                    "o": [
                      [0, 0],
                      [0, 0],
                      [0, 0],
                      [0, 0]
                    ],
                    "v": [
                      [277.469, -104.5],
                      [244.469, -104.5],
                      [244.469, 64],
                      [277.469, 64]
                    ],
                    "c": true
                  }
                ]
              }
            ],
            "ix": 1
          },
          "o": { "a": 0, "k": 100, "ix": 3 },
          "x": { "a": 0, "k": 0, "ix": 4 },
          "nm": "Mask 2"
        }
      ],
      "shapes": [
        {
          "ty": "gr",
          "it": [
            {
              "ind": 0,
              "ty": "sh",
              "ix": 1,
              "ks": {
                "a": 0,
                "k": {
                  "i": [
                    [0, 0.25],
                    [0, 0],
                    [0, 0],
                    [0, 0],
                    [0, 0],
                    [0, 0],
                    [0, 0],
                    [0, 0],
                    [0, 0],
                    [0, 0],
                    [0, 0],
                    [0, 0],
                    [0, 0],
                    [0, 0],
                    [0, 0],
                    [0, 0],
                    [0, 0],
                    [0, 0],
                    [0, 0],
                    [0, 0],
                    [0, 0],
                    [0, 0],
                    [0, 0],
                    [0, 0],
                    [0, 0],
                    [0, 0],
                    [0, 0],
                    [0, 0],
                    [0, 0],
                    [0, 0],
                    [0, 0],
                    [0, 0],
                    [0, 0],
                    [0, 0],
                    [0, 0],
                    [0, 0],
                    [0, 0],
                    [0, 0],
                    [0, 0],
                    [0, 0],
                    [0, 0],
                    [0, 0],
                    [0, 0],
                    [0, 0],
                    [0, 0],
                    [0, 0]
                  ],
                  "o": [
                    [0, -0.25],
                    [0, 0],
                    [0, 0],
                    [0, 0],
                    [0, 0],
                    [0, 0],
                    [0, 0],
                    [0, 0],
                    [0, 0],
                    [0, 0],
                    [0, 0],
                    [0, 0],
                    [0, 0],
                    [0, 0],
                    [0, 0],
                    [0, 0],
                    [0, 0],
                    [0, 0],
                    [0, 0],
                    [0, 0],
                    [0, 0],
                    [0, 0],
                    [0, 0],
                    [0, 0],
                    [0, 0],
                    [0, 0],
                    [0, 0],
                    [0, 0],
                    [0, 0],
                    [0, 0],
                    [0, 0],
                    [0, 0],
                    [0, 0],
                    [0, 0],
                    [0, 0],
                    [0, 0],
                    [0, 0],
                    [0, 0],
                    [0, 0],
                    [0, 0],
                    [0, 0],
                    [0, 0],
                    [0, 0],
                    [0, 0],
                    [0, 0],
                    [0, 0]
                  ],
                  "v": [
                    [-219.688, -20.75],
                    [-189, -21],
                    [-179.875, -26],
                    [-171.5, -21],
                    [-163, -21],
                    [-160.125, -15.125],
                    [-157, -21],
                    [-150.125, -21],
                    [-146.25, -33],
                    [-140.625, -21],
                    [-135.25, -21],
                    [-133.75, -17.5],
                    [-127.125, -87.375],
                    [-117.75, 20.625],
                    [-112.875, -21],
                    [-100.375, -21],
                    [-88, -35],
                    [-77.625, -21],
                    [-45, -21],
                    [-36.125, -26.25],
                    [-25.875, -21],
                    [-17.875, -21],
                    [-14.875, -14.75],
                    [-12.75, -21],
                    [-5.875, -21],
                    [-1, -32.875],
                    [4.125, -21],
                    [9, -21],
                    [10.875, -16.25],
                    [18.375, -87.5],
                    [26.125, 20],
                    [32.25, -21],
                    [77.375, -21],
                    [85.75, -26.375],
                    [92.25, -21],
                    [101.25, -21],
                    [105.5, -14.625],
                    [108.375, -21],
                    [114.5, -21],
                    [121.25, -32.5],
                    [125.5, -21],
                    [134.625, -21],
                    [140.25, -14.25],
                    [146.625, -88.125],
                    [156.5, 21.125],
                    [161.625, 9.125]
                  ],
                  "c": false
                },
                "ix": 2
              },
              "nm": "Path 1",
              "mn": "ADBE Vector Shape - Group",
              "hd": false
            },
            {
              "ty": "st",
              "c": { "a": 0, "k": [0.951372692632, 0.302200706332, 0.357183299345, 1], "ix": 3 },
              "o": { "a": 0, "k": 100, "ix": 4 },
              "w": { "a": 0, "k": 1, "ix": 5 },
              "lc": 1,
              "lj": 1,
              "ml": 4,
              "bm": 0,
              "nm": "Stroke 1",
              "mn": "ADBE Vector Graphic - Stroke",
              "hd": false
            },
            {
              "ty": "tr",
              "p": { "a": 0, "k": [0, 0], "ix": 2 },
              "a": { "a": 0, "k": [0, 0], "ix": 1 },
              "s": { "a": 0, "k": [100, 100], "ix": 3 },
              "r": { "a": 0, "k": 0, "ix": 6 },
              "o": { "a": 0, "k": 100, "ix": 7 },
              "sk": { "a": 0, "k": 0, "ix": 4 },
              "sa": { "a": 0, "k": 0, "ix": 5 },
              "nm": "Transform"
            }
          ],
          "nm": "Shape 1",
          "np": 3,
          "cix": 2,
          "bm": 0,
          "ix": 1,
          "mn": "ADBE Vector Group",
          "hd": false
        }
      ],
      "ip": 2,
      "op": 902,
      "st": 2,
      "ct": 1,
      "bm": 0
    },
    {
      "ddd": 0,
      "ind": 3,
      "ty": 4,
      "nm": "line 2",
      "sr": 1,
      "ks": {
        "o": {
          "a": 1,
          "k": [
            { "i": { "x": [0.833], "y": [0.833] }, "o": { "x": [0.167], "y": [0.167] }, "t": 74, "s": [100] },
            { "t": 81, "s": [0] }
          ],
          "ix": 11
        },
        "r": { "a": 0, "k": 0, "ix": 10 },
        "p": { "a": 0, "k": [250, 250, 0], "ix": 2, "l": 2 },
        "a": { "a": 0, "k": [-29.031, -33.5, 0], "ix": 1, "l": 2 },
        "s": { "a": 0, "k": [100, 100, 100], "ix": 6, "l": 2 }
      },
      "ao": 0,
      "hasMask": true,
      "masksProperties": [
        {
          "inv": false,
          "mode": "s",
          "pt": {
            "a": 1,
            "k": [
              {
                "i": { "x": 0.129, "y": 1 },
                "o": { "x": 0.167, "y": 0.167 },
                "t": 0,
                "s": [
                  {
                    "i": [
                      [0, 0],
                      [0, 0],
                      [0, 0],
                      [0, 0]
                    ],
                    "o": [
                      [0, 0],
                      [0, 0],
                      [0, 0],
                      [0, 0]
                    ],
                    "v": [
                      [201.969, -104.5],
                      [-236.031, -104.5],
                      [-236.031, 64],
                      [201.969, 64]
                    ],
                    "c": true
                  }
                ]
              },
              {
                "t": 74,
                "s": [
                  {
                    "i": [
                      [0, 0],
                      [0, 0],
                      [0, 0],
                      [0, 0]
                    ],
                    "o": [
                      [0, 0],
                      [0, 0],
                      [0, 0],
                      [0, 0]
                    ],
                    "v": [
                      [244.469, -104.5],
                      [223.469, -104.5],
                      [223.469, 64],
                      [244.469, 64]
                    ],
                    "c": true
                  }
                ]
              }
            ],
            "ix": 1
          },
          "o": { "a": 0, "k": 100, "ix": 3 },
          "x": { "a": 0, "k": 0, "ix": 4 },
          "nm": "Mask 1"
        },
        {
          "inv": false,
          "mode": "i",
          "pt": {
            "a": 1,
            "k": [
              {
                "i": { "x": 0.126, "y": 1 },
                "o": { "x": 0.167, "y": 0.167 },
                "t": 5,
                "s": [
                  {
                    "i": [
                      [0, 0],
                      [0, 0],
                      [0, 0],
                      [0, 0]
                    ],
                    "o": [
                      [0, 0],
                      [0, 0],
                      [0, 0],
                      [0, 0]
                    ],
                    "v": [
                      [303.469, -104.5],
                      [-236.031, -104.5],
                      [-236.031, 64],
                      [303.469, 64]
                    ],
                    "c": true
                  }
                ]
              },
              {
                "t": 81,
                "s": [
                  {
                    "i": [
                      [0, 0],
                      [0, 0],
                      [0, 0],
                      [0, 0]
                    ],
                    "o": [
                      [0, 0],
                      [0, 0],
                      [0, 0],
                      [0, 0]
                    ],
                    "v": [
                      [272.969, -104.5],
                      [239.969, -104.5],
                      [239.969, 64],
                      [272.969, 64]
                    ],
                    "c": true
                  }
                ]
              }
            ],
            "ix": 1
          },
          "o": { "a": 0, "k": 100, "ix": 3 },
          "x": { "a": 0, "k": 0, "ix": 4 },
          "nm": "Mask 2"
        }
      ],
      "shapes": [
        {
          "ty": "gr",
          "it": [
            {
              "ind": 0,
              "ty": "sh",
              "ix": 1,
              "ks": {
                "a": 0,
                "k": {
                  "i": [
                    [0, 0.25],
                    [0, 0],
                    [0, 0],
                    [0, 0],
                    [0, 0],
                    [0, 0],
                    [0, 0],
                    [0, 0],
                    [0, 0],
                    [0, 0],
                    [0, 0],
                    [0, 0],
                    [0, 0],
                    [0, 0],
                    [0, 0],
                    [0, 0],
                    [0, 0],
                    [0, 0],
                    [0, 0],
                    [0, 0],
                    [0, 0],
                    [0, 0],
                    [0, 0],
                    [0, 0],
                    [0, 0],
                    [0, 0],
                    [0, 0],
                    [0, 0],
                    [0, 0],
                    [0, 0],
                    [0, 0],
                    [0, 0],
                    [0, 0],
                    [0, 0],
                    [0, 0],
                    [0, 0],
                    [0, 0],
                    [0, 0],
                    [0, 0],
                    [0, 0],
                    [0, 0],
                    [0, 0],
                    [0, 0],
                    [0, 0],
                    [0, 0],
                    [0, 0]
                  ],
                  "o": [
                    [0, -0.25],
                    [0, 0],
                    [0, 0],
                    [0, 0],
                    [0, 0],
                    [0, 0],
                    [0, 0],
                    [0, 0],
                    [0, 0],
                    [0, 0],
                    [0, 0],
                    [0, 0],
                    [0, 0],
                    [0, 0],
                    [0, 0],
                    [0, 0],
                    [0, 0],
                    [0, 0],
                    [0, 0],
                    [0, 0],
                    [0, 0],
                    [0, 0],
                    [0, 0],
                    [0, 0],
                    [0, 0],
                    [0, 0],
                    [0, 0],
                    [0, 0],
                    [0, 0],
                    [0, 0],
                    [0, 0],
                    [0, 0],
                    [0, 0],
                    [0, 0],
                    [0, 0],
                    [0, 0],
                    [0, 0],
                    [0, 0],
                    [0, 0],
                    [0, 0],
                    [0, 0],
                    [0, 0],
                    [0, 0],
                    [0, 0],
                    [0, 0],
                    [0, 0]
                  ],
                  "v": [
                    [-219.688, -20.75],
                    [-189, -21],
                    [-179.875, -26],
                    [-171.5, -21],
                    [-163, -21],
                    [-160.125, -15.125],
                    [-157, -21],
                    [-150.125, -21],
                    [-146.25, -33],
                    [-140.625, -21],
                    [-135.25, -21],
                    [-133.75, -17.5],
                    [-127.125, -87.375],
                    [-117.75, 20.625],
                    [-112.875, -21],
                    [-100.375, -21],
                    [-88, -35],
                    [-77.625, -21],
                    [-45, -21],
                    [-36.125, -26.25],
                    [-25.875, -21],
                    [-17.875, -21],
                    [-14.875, -14.75],
                    [-12.75, -21],
                    [-5.875, -21],
                    [-1, -32.875],
                    [4.125, -21],
                    [9, -21],
                    [10.875, -16.25],
                    [18.375, -87.5],
                    [26.125, 20],
                    [32.25, -21],
                    [77.375, -21],
                    [85.75, -26.375],
                    [92.25, -21],
                    [101.25, -21],
                    [105.5, -14.625],
                    [108.375, -21],
                    [114.5, -21],
                    [121.25, -32.5],
                    [125.5, -21],
                    [134.625, -21],
                    [140.25, -14.25],
                    [146.625, -88.125],
                    [156.5, 21.125],
                    [161.625, 9.125]
                  ],
                  "c": false
                },
                "ix": 2
              },
              "nm": "Path 1",
              "mn": "ADBE Vector Shape - Group",
              "hd": false
            },
            {
              "ty": "st",
              "c": { "a": 0, "k": [0.951372692632, 0.573808258655, 0.60578661152, 1], "ix": 3 },
              "o": { "a": 0, "k": 100, "ix": 4 },
              "w": { "a": 0, "k": 1.5, "ix": 5 },
              "lc": 1,
              "lj": 1,
              "ml": 4,
              "bm": 0,
              "nm": "Stroke 1",
              "mn": "ADBE Vector Graphic - Stroke",
              "hd": false
            },
            {
              "ty": "tr",
              "p": { "a": 0, "k": [0, 0], "ix": 2 },
              "a": { "a": 0, "k": [0, 0], "ix": 1 },
              "s": { "a": 0, "k": [100, 100], "ix": 3 },
              "r": { "a": 0, "k": 0, "ix": 6 },
              "o": { "a": 0, "k": 100, "ix": 7 },
              "sk": { "a": 0, "k": 0, "ix": 4 },
              "sa": { "a": 0, "k": 0, "ix": 5 },
              "nm": "Transform"
            }
          ],
          "nm": "Shape 1",
          "np": 3,
          "cix": 2,
          "bm": 0,
          "ix": 1,
          "mn": "ADBE Vector Group",
          "hd": false
        }
      ],
      "ip": 0,
      "op": 900,
      "st": 0,
      "ct": 1,
      "bm": 0
    }
  ],
  "markers": [{ "tm": 66, "cm": "", "dr": 0 }],
  "props": {}
}
